{"errors":[],"warnings":["./node_modules/@bodiless/gatsby-theme-bodiless/dist/tailwindcss/getBodilessConfigs.js 13:787-810\nCritical dependency: the request of a dependency is an expression","./node_modules/@bodiless/gatsby-theme-bodiless/dist/fsLogHandler.js\nModule not found: Error: Can't resolve 'fs' in '/Users/eriksummerfield/dev/e2thex.org/node_modules/@bodiless/gatsby-theme-bodiless/dist'"],"namedChunkGroups":{"polyfill":{"chunks":[9,17],"assets":["webpack-runtime-e16a84c7fe867cf43ad3.js","webpack-runtime-e16a84c7fe867cf43ad3.js.map","polyfill-a439e5b97fd82518defd.js","polyfill-a439e5b97fd82518defd.js.map"],"children":{},"childAssets":{}},"app":{"chunks":[9,1,0,10],"assets":["webpack-runtime-e16a84c7fe867cf43ad3.js","webpack-runtime-e16a84c7fe867cf43ad3.js.map","styles.8ab279c5951e6da36490.css","styles-e9d24b1846c7d6eb9685.js","styles-e9d24b1846c7d6eb9685.js.map","framework-1fecebff3898e4cd29f2.js","framework-1fecebff3898e4cd29f2.js.map","app-9ec7ff732e9a4968f1a1.js","app-9ec7ff732e9a4968f1a1.js.map"],"children":{},"childAssets":{}},"component---src-data-pages-404-index-tsx":{"chunks":[1,0,2,3,6,4,8,5,7,11],"assets":["styles.8ab279c5951e6da36490.css","styles-e9d24b1846c7d6eb9685.js","styles-e9d24b1846c7d6eb9685.js.map","framework-1fecebff3898e4cd29f2.js","framework-1fecebff3898e4cd29f2.js.map","29107295-31903c7cd144f52709bf.js","29107295-31903c7cd144f52709bf.js.map","777cf710-77f48b32b3456b0ee946.js","777cf710-77f48b32b3456b0ee946.js.map","d3048c20-fd27e174758b6307ebb4.js","d3048c20-fd27e174758b6307ebb4.js.map","8313d723-25dfd1227fcc165e787c.js","8313d723-25dfd1227fcc165e787c.js.map","b5f2ed29-bc0d0451ec082d46fa34.js","b5f2ed29-bc0d0451ec082d46fa34.js.map","commons-15c759563eef7d6b998e.js","commons-15c759563eef7d6b998e.js.map","8e4e107a75161fbf26a86f012ca51c6955e3b50a-0993f6e3f1e6609cb64c.js","8e4e107a75161fbf26a86f012ca51c6955e3b50a-0993f6e3f1e6609cb64c.js.map","component---src-data-pages-404-index-tsx-d242253a5bce4cce146e.js","component---src-data-pages-404-index-tsx-d242253a5bce4cce146e.js.map"],"children":{},"childAssets":{}},"component---src-data-pages-forkthesystem-scruminraci-index-tsx":{"chunks":[1,0,2,3,6,4,8,5,7,12],"assets":["styles.8ab279c5951e6da36490.css","styles-e9d24b1846c7d6eb9685.js","styles-e9d24b1846c7d6eb9685.js.map","framework-1fecebff3898e4cd29f2.js","framework-1fecebff3898e4cd29f2.js.map","29107295-31903c7cd144f52709bf.js","29107295-31903c7cd144f52709bf.js.map","777cf710-77f48b32b3456b0ee946.js","777cf710-77f48b32b3456b0ee946.js.map","d3048c20-fd27e174758b6307ebb4.js","d3048c20-fd27e174758b6307ebb4.js.map","8313d723-25dfd1227fcc165e787c.js","8313d723-25dfd1227fcc165e787c.js.map","b5f2ed29-bc0d0451ec082d46fa34.js","b5f2ed29-bc0d0451ec082d46fa34.js.map","commons-15c759563eef7d6b998e.js","commons-15c759563eef7d6b998e.js.map","8e4e107a75161fbf26a86f012ca51c6955e3b50a-0993f6e3f1e6609cb64c.js","8e4e107a75161fbf26a86f012ca51c6955e3b50a-0993f6e3f1e6609cb64c.js.map","component---src-data-pages-forkthesystem-scruminraci-index-tsx-d73658ae4ed50c8f61b1.js","component---src-data-pages-forkthesystem-scruminraci-index-tsx-d73658ae4ed50c8f61b1.js.map"],"children":{},"childAssets":{}},"component---src-data-pages-index-tsx":{"chunks":[1,0,2,3,6,4,8,5,7,13],"assets":["styles.8ab279c5951e6da36490.css","styles-e9d24b1846c7d6eb9685.js","styles-e9d24b1846c7d6eb9685.js.map","framework-1fecebff3898e4cd29f2.js","framework-1fecebff3898e4cd29f2.js.map","29107295-31903c7cd144f52709bf.js","29107295-31903c7cd144f52709bf.js.map","777cf710-77f48b32b3456b0ee946.js","777cf710-77f48b32b3456b0ee946.js.map","d3048c20-fd27e174758b6307ebb4.js","d3048c20-fd27e174758b6307ebb4.js.map","8313d723-25dfd1227fcc165e787c.js","8313d723-25dfd1227fcc165e787c.js.map","b5f2ed29-bc0d0451ec082d46fa34.js","b5f2ed29-bc0d0451ec082d46fa34.js.map","commons-15c759563eef7d6b998e.js","commons-15c759563eef7d6b998e.js.map","8e4e107a75161fbf26a86f012ca51c6955e3b50a-0993f6e3f1e6609cb64c.js","8e4e107a75161fbf26a86f012ca51c6955e3b50a-0993f6e3f1e6609cb64c.js.map","component---src-data-pages-index-tsx-53d0b9526713bf7382cc.js","component---src-data-pages-index-tsx-53d0b9526713bf7382cc.js.map"],"children":{},"childAssets":{}},"component---src-data-pages-search-index-tsx":{"chunks":[1,0,2,3,6,4,5,14],"assets":["styles.8ab279c5951e6da36490.css","styles-e9d24b1846c7d6eb9685.js","styles-e9d24b1846c7d6eb9685.js.map","framework-1fecebff3898e4cd29f2.js","framework-1fecebff3898e4cd29f2.js.map","29107295-31903c7cd144f52709bf.js","29107295-31903c7cd144f52709bf.js.map","777cf710-77f48b32b3456b0ee946.js","777cf710-77f48b32b3456b0ee946.js.map","d3048c20-fd27e174758b6307ebb4.js","d3048c20-fd27e174758b6307ebb4.js.map","8313d723-25dfd1227fcc165e787c.js","8313d723-25dfd1227fcc165e787c.js.map","commons-15c759563eef7d6b998e.js","commons-15c759563eef7d6b998e.js.map","component---src-data-pages-search-index-tsx-d968886596107988442e.js","component---src-data-pages-search-index-tsx-d968886596107988442e.js.map"],"children":{},"childAssets":{}},"component---src-templates-default-jsx":{"chunks":[1,0,2,3,6,4,8,5,7,15],"assets":["styles.8ab279c5951e6da36490.css","styles-e9d24b1846c7d6eb9685.js","styles-e9d24b1846c7d6eb9685.js.map","framework-1fecebff3898e4cd29f2.js","framework-1fecebff3898e4cd29f2.js.map","29107295-31903c7cd144f52709bf.js","29107295-31903c7cd144f52709bf.js.map","777cf710-77f48b32b3456b0ee946.js","777cf710-77f48b32b3456b0ee946.js.map","d3048c20-fd27e174758b6307ebb4.js","d3048c20-fd27e174758b6307ebb4.js.map","8313d723-25dfd1227fcc165e787c.js","8313d723-25dfd1227fcc165e787c.js.map","b5f2ed29-bc0d0451ec082d46fa34.js","b5f2ed29-bc0d0451ec082d46fa34.js.map","commons-15c759563eef7d6b998e.js","commons-15c759563eef7d6b998e.js.map","8e4e107a75161fbf26a86f012ca51c6955e3b50a-0993f6e3f1e6609cb64c.js","8e4e107a75161fbf26a86f012ca51c6955e3b50a-0993f6e3f1e6609cb64c.js.map","component---src-templates-default-jsx-b4618d4e8d13ddafe3ac.js","component---src-templates-default-jsx-b4618d4e8d13ddafe3ac.js.map"],"children":{},"childAssets":{}},"component---src-templates-post-jsx":{"chunks":[1,0,2,3,6,4,8,5,7,16],"assets":["styles.8ab279c5951e6da36490.css","styles-e9d24b1846c7d6eb9685.js","styles-e9d24b1846c7d6eb9685.js.map","framework-1fecebff3898e4cd29f2.js","framework-1fecebff3898e4cd29f2.js.map","29107295-31903c7cd144f52709bf.js","29107295-31903c7cd144f52709bf.js.map","777cf710-77f48b32b3456b0ee946.js","777cf710-77f48b32b3456b0ee946.js.map","d3048c20-fd27e174758b6307ebb4.js","d3048c20-fd27e174758b6307ebb4.js.map","8313d723-25dfd1227fcc165e787c.js","8313d723-25dfd1227fcc165e787c.js.map","b5f2ed29-bc0d0451ec082d46fa34.js","b5f2ed29-bc0d0451ec082d46fa34.js.map","commons-15c759563eef7d6b998e.js","commons-15c759563eef7d6b998e.js.map","8e4e107a75161fbf26a86f012ca51c6955e3b50a-0993f6e3f1e6609cb64c.js","8e4e107a75161fbf26a86f012ca51c6955e3b50a-0993f6e3f1e6609cb64c.js.map","component---src-templates-post-jsx-e4e66b6fd0843561faaf.js","component---src-templates-post-jsx-e4e66b6fd0843561faaf.js.map"],"children":{},"childAssets":{}}},"assetsByChunkName":{"polyfill":["webpack-runtime-e16a84c7fe867cf43ad3.js","polyfill-a439e5b97fd82518defd.js"],"app":["webpack-runtime-e16a84c7fe867cf43ad3.js","styles.8ab279c5951e6da36490.css","styles-e9d24b1846c7d6eb9685.js","framework-1fecebff3898e4cd29f2.js","app-9ec7ff732e9a4968f1a1.js"],"component---src-data-pages-404-index-tsx":["styles.8ab279c5951e6da36490.css","styles-e9d24b1846c7d6eb9685.js","framework-1fecebff3898e4cd29f2.js","29107295-31903c7cd144f52709bf.js","777cf710-77f48b32b3456b0ee946.js","d3048c20-fd27e174758b6307ebb4.js","8313d723-25dfd1227fcc165e787c.js","b5f2ed29-bc0d0451ec082d46fa34.js","commons-15c759563eef7d6b998e.js","8e4e107a75161fbf26a86f012ca51c6955e3b50a-0993f6e3f1e6609cb64c.js","component---src-data-pages-404-index-tsx-d242253a5bce4cce146e.js"],"component---src-data-pages-forkthesystem-scruminraci-index-tsx":["styles.8ab279c5951e6da36490.css","styles-e9d24b1846c7d6eb9685.js","framework-1fecebff3898e4cd29f2.js","29107295-31903c7cd144f52709bf.js","777cf710-77f48b32b3456b0ee946.js","d3048c20-fd27e174758b6307ebb4.js","8313d723-25dfd1227fcc165e787c.js","b5f2ed29-bc0d0451ec082d46fa34.js","commons-15c759563eef7d6b998e.js","8e4e107a75161fbf26a86f012ca51c6955e3b50a-0993f6e3f1e6609cb64c.js","component---src-data-pages-forkthesystem-scruminraci-index-tsx-d73658ae4ed50c8f61b1.js"],"component---src-data-pages-index-tsx":["styles.8ab279c5951e6da36490.css","styles-e9d24b1846c7d6eb9685.js","framework-1fecebff3898e4cd29f2.js","29107295-31903c7cd144f52709bf.js","777cf710-77f48b32b3456b0ee946.js","d3048c20-fd27e174758b6307ebb4.js","8313d723-25dfd1227fcc165e787c.js","b5f2ed29-bc0d0451ec082d46fa34.js","commons-15c759563eef7d6b998e.js","8e4e107a75161fbf26a86f012ca51c6955e3b50a-0993f6e3f1e6609cb64c.js","component---src-data-pages-index-tsx-53d0b9526713bf7382cc.js"],"component---src-data-pages-search-index-tsx":["styles.8ab279c5951e6da36490.css","styles-e9d24b1846c7d6eb9685.js","framework-1fecebff3898e4cd29f2.js","29107295-31903c7cd144f52709bf.js","777cf710-77f48b32b3456b0ee946.js","d3048c20-fd27e174758b6307ebb4.js","8313d723-25dfd1227fcc165e787c.js","commons-15c759563eef7d6b998e.js","component---src-data-pages-search-index-tsx-d968886596107988442e.js"],"component---src-templates-default-jsx":["styles.8ab279c5951e6da36490.css","styles-e9d24b1846c7d6eb9685.js","framework-1fecebff3898e4cd29f2.js","29107295-31903c7cd144f52709bf.js","777cf710-77f48b32b3456b0ee946.js","d3048c20-fd27e174758b6307ebb4.js","8313d723-25dfd1227fcc165e787c.js","b5f2ed29-bc0d0451ec082d46fa34.js","commons-15c759563eef7d6b998e.js","8e4e107a75161fbf26a86f012ca51c6955e3b50a-0993f6e3f1e6609cb64c.js","component---src-templates-default-jsx-b4618d4e8d13ddafe3ac.js"],"component---src-templates-post-jsx":["styles.8ab279c5951e6da36490.css","styles-e9d24b1846c7d6eb9685.js","framework-1fecebff3898e4cd29f2.js","29107295-31903c7cd144f52709bf.js","777cf710-77f48b32b3456b0ee946.js","d3048c20-fd27e174758b6307ebb4.js","8313d723-25dfd1227fcc165e787c.js","b5f2ed29-bc0d0451ec082d46fa34.js","commons-15c759563eef7d6b998e.js","8e4e107a75161fbf26a86f012ca51c6955e3b50a-0993f6e3f1e6609cb64c.js","component---src-templates-post-jsx-e4e66b6fd0843561faaf.js"]}}